Workbook
Name DataTapeFirstCell: DATA!$A$2

Sheet DATA
A1: Loan ID | B1: Product Type | C1: Lien Position | D1: Address | E1: City | F1: State | G1: Zip Code | H1: Number of Properties | I1: Number of Units | J1: UPB | K1: Appraisal Date | L1: Appraisal Amount | M1: Property Acquisition Date | N1: Property Acquisition Price | O1: LTAIV | P1: LTC | Q1: Term (Months) | R1: Origination Date | S1: First Payment Date | T1: Current Maturity Date | U1: Next Payment Due Date | V1: Elig_FirstLien | W1: Current | X1: Elig_UPB | Y1: Elig_OriginationDate | Z1: Elig_AppraisalDate | AA1: Loan's Eligibility
A2: 1 | B2: RTL | C2: First | D2: 123 Maple St | E2: Springfield | F2: IL | G2: 62704 | H2: 1 | I2: 3 | J2: 212000 | K2: 46010 | L2: 312000 | M2: 45825 | N2: 275000 | O2: 0.67948718 | P2: 0.77090909 | Q2: 30 | R2: 45977 | S2: 45992 | T2: 46889 | U2: 46054 | V2: =DATA!$C2 = "First" -> TRUE | W2: =DATA!$U2 >= DATE(2026, 1, 1) - 30 -> TRUE | X2: =DATA!$J2 <= 800000 -> TRUE | Y2: =AND(DATA!$R2 >= DATE(2026,1,1) - 360, DATA!$R2 <=DATE(2026,1,1)) -> TRUE | Z2: =AND(DATA!$K2 >= DATE(2026,1,1) - 60, DATA!$K2 <= DATE(2026,1,1)) -> TRUE | AA2: Y
A3: 2 | B3: RTL | C3: First | D3: 456 Oak Ave | E3: Madison | F3: WI | G3: 53703 | H3: 1 | I3: 1 | J3: 578000 | K3: 45940 | L3: 906000 | M3: 45723 | N3: 854000 | O3: 0.63796909 | P3: 0.67681499 | Q3: 30 | R3: 45881 | S3: 45901 | T3: 46795 | U3: 46054 | V3: =DATA!$C3 = "First" -> TRUE | W3: =DATA!$U3 >= DATE(2026, 1, 1) - 30 -> TRUE | X3: =DATA!$J3 <= 800000 -> TRUE | Y3: =AND(DATA!$R3 >= DATE(2026,1,1) - 360, DATA!$R3 <=DATE(2026,1,1)) -> TRUE | Z3: =AND(DATA!$K3 >= DATE(2026,1,1) - 60, DATA!$K3 <= DATE(2026,1,1)) -> FALSE | AA3: N
A4: 3 | B4: RTL | C4: First | D4: 789 Pine Rd | E4: Boulder | F4: CO | G4: 80302 | H4: 1 | I4: 1 | J4: 199000 | K4: 45977 | L4: 360000 | M4: 45814 | N4: 277000 | O4: 0.55277778 | P4: 0.71841155 | Q4: 60 | R4: 45840 | S4: 45870 | T4: 47666 | U4: 46054 | V4: =DATA!$C4 = "First" -> TRUE | W4: =DATA!$U4 >= DATE(2026, 1, 1) - 30 -> TRUE | X4: =DATA!$J4 <= 800000 -> TRUE | Y4: =AND(DATA!$R4 >= DATE(2026,1,1) - 360, DATA!$R4 <=DATE(2026,1,1)) -> TRUE | Z4: =AND(DATA!$K4 >= DATE(2026,1,1) - 60, DATA!$K4 <= DATE(2026,1,1)) -> TRUE | AA4: Y
A5: 4 | B5: RTL | C5: First | D5: 101 Cedar Ln | E5: Austin | F5: TX | G5: 78745 | H5: 1 | I5: 1 | J5: 540000 | K5: 45756 | L5: 1155000 | M5: 45482 | N5: 853000 | O5: 0.46753247 | P5: 0.63305979 | Q5: 30 | R5: 45548 | S5: 45566 | T5: 46459 | U5: 46054 | V5: =DATA!$C5 = "First" -> TRUE | W5: =DATA!$U5 >= DATE(2026, 1, 1) - 30 -> TRUE | X5: =DATA!$J5 <= 800000 -> TRUE | Y5: =AND(DATA!$R5 >= DATE(2026,1,1) - 360, DATA!$R5 <=DATE(2026,1,1)) -> FALSE | Z5: =AND(DATA!$K5 >= DATE(2026,1,1) - 60, DATA!$K5 <= DATE(2026,1,1)) -> FALSE | AA5: N
A6: 5 | B6: RTL | C6: First | D6: 202 Birch Blvd | E6: Salem | F6: OR | G6: 97301 | H6: 1 | I6: 4 | J6: 319000 | K6: 45811 | L6: 740000 | M6: 45662 | N6: 534000 | O6: 0.43108108 | P6: 0.59737828 | Q6: 36 | R6: 45755 | S6: 45778 | T6: 46851 | U6: 46054 | V6: =DATA!$C6 = "First" -> TRUE | W6: =DATA!$U6 >= DATE(2026, 1, 1) - 30 -> TRUE | X6: =DATA!$J6 <= 800000 -> TRUE | Y6: =AND(DATA!$R6 >= DATE(2026,1,1) - 360, DATA!$R6 <=DATE(2026,1,1)) -> TRUE | Z6: =AND(DATA!$K6 >= DATE(2026,1,1) - 60, DATA!$K6 <= DATE(2026,1,1)) -> FALSE | AA6: N
A7: 6 | B7: RTL | C7: First | D7: 303 Walnut St | E7: Columbus | F7: OH | G7: 43215 | H7: 1 | I7: 1 | J7: 230000 | K7: 45653 | L7: 408000 | M7: 45334 | N7: 349000 | O7: 0.56372549 | P7: 0.65902579 | Q7: 36 | R7: 45417 | S7: 45444 | T7: 46512 | U7: 46054 | V7: =DATA!$C7 = "First" -> TRUE | W7: =DATA!$U7 >= DATE(2026, 1, 1) - 30 -> TRUE | X7: =DATA!$J7 <= 800000 -> TRUE | Y7: =AND(DATA!$R7 >= DATE(2026,1,1) - 360, DATA!$R7 <=DATE(2026,1,1)) -> FALSE | Z7: =AND(DATA!$K7 >= DATE(2026,1,1) - 60, DATA!$K7 <= DATE(2026,1,1)) -> FALSE | AA7: N
A8: 7 | B8: RTL | C8: First | D8: 404 Cherry Ave | E8: Ann Arbor | F8: MI | G8: 48104 | H8: 1 | I8: 1 | J8: 469000 | K8: 45538 | L8: 1097000 | M8: 45304 | N8: 799000 | O8: 0.42752963 | P8: 0.58698373 | Q8: 24 | R8: 45367 | S8: 45383 | T8: 46097 | U8: 46054 | V8: =DATA!$C8 = "First" -> TRUE | W8: =DATA!$U8 >= DATE(2026, 1, 1) - 30 -> TRUE | X8: =DATA!$J8 <= 800000 -> TRUE | Y8: =AND(DATA!$R8 >= DATE(2026,1,1) - 360, DATA!$R8 <=DATE(2026,1,1)) -> FALSE | Z8: =AND(DATA!$K8 >= DATE(2026,1,1) - 60, DATA!$K8 <= DATE(2026,1,1)) -> FALSE | AA8: N
A9: 8 | B9: RTL | C9: First | D9: 505 Elm St | E9: Raleigh | F9: NC | G9: 27601 | H9: 1 | I9: 1 | J9: 720000 | K9: 45833 | L9: 1039000 | M9: 45603 | N9: 883000 | O9: 0.69297401 | P9: 0.81540204 | Q9: 30 | R9: 45623 | S9: 45627 | T9: 46534 | U9: 46054 | V9: =DATA!$C9 = "First" -> TRUE | W9: =DATA!$U9 >= DATE(2026, 1, 1) - 30 -> TRUE | X9: =DATA!$J9 <= 800000 -> TRUE | Y9: =AND(DATA!$R9 >= DATE(2026,1,1) - 360, DATA!$R9 <=DATE(2026,1,1)) -> FALSE | Z9: =AND(DATA!$K9 >= DATE(2026,1,1) - 60, DATA!$K9 <= DATE(2026,1,1)) -> FALSE | AA9: N
A10: 9 | B10: RTL | C10: First | D10: 606 Willow Dr | E10: Provo | F10: UT | G10: 84601 | H10: 1 | I10: 1 | J10: 573000 | K10: 45642 | L10: 1067000 | M10: 45225 | N10: 927000 | O10: 0.53701968 | P10: 0.61812298 | Q10: 24 | R10: 45394 | S10: 45413 | T10: 46124 | U10: 46054 | V10: =DATA!$C10 = "First" -> TRUE | W10: =DATA!$U10 >= DATE(2026, 1, 1) - 30 -> TRUE | X10: =DATA!$J10 <= 800000 -> TRUE | Y10: =AND(DATA!$R10 >= DATE(2026,1,1) - 360, DATA!$R10 <=DATE(2026,1,1)) -> FALSE | Z10: =AND(DATA!$K10 >= DATE(2026,1,1) - 60, DATA!$K10 <= DATE(2026,1,1)) -> FALSE | AA10: N
A11: 10 | B11: RTL | C11: First | D11: 707 Aspen Ct | E11: Flagstaff | F11: AZ | G11: 86001 | H11: 1 | I11: 1 | J11: 405000 | K11: 45632 | L11: 813000 | M11: 45406 | N11: 639000 | O11: 0.49815498 | P11: 0.63380282 | Q11: 36 | R11: 45561 | S11: 45566 | T11: 46656 | U11: 46054 | V11: =DATA!$C11 = "First" -> TRUE | W11: =DATA!$U11 >= DATE(2026, 1, 1) - 30 -> TRUE | X11: =DATA!$J11 <= 800000 -> TRUE | Y11: =AND(DATA!$R11 >= DATE(2026,1,1) - 360, DATA!$R11 <=DATE(2026,1,1)) -> FALSE | Z11: =AND(DATA!$K11 >= DATE(2026,1,1) - 60, DATA!$K11 <= DATE(2026,1,1)) -> FALSE | AA11: N
A12: 11 | B12: RTL | C12: First | D12: 808 Sycamore Rd | E12: Athens | F12: GA | G12: 30601 | H12: 1 | I12: 1 | J12: 348000 | K12: 45887 | L12: 601000 | M12: 45612 | N12: 464000 | O12: 0.57903494 | P12: 0.75 | Q12: 24 | R12: 45702 | S12: 45717 | T12: 46432 | U12: 46054 | V12: =DATA!$C12 = "First" -> TRUE | W12: =DATA!$U12 >= DATE(2026, 1, 1) - 30 -> TRUE | X12: =DATA!$J12 <= 800000 -> TRUE | Y12: =AND(DATA!$R12 >= DATE(2026,1,1) - 360, DATA!$R12 <=DATE(2026,1,1)) -> TRUE | Z12: =AND(DATA!$K12 >= DATE(2026,1,1) - 60, DATA!$K12 <= DATE(2026,1,1)) -> FALSE | AA12: N
A13: 12 | B13: RTL | C13: First | D13: 909 Poplar St | E13: Lexington | F13: KY | G13: 40507 | H13: 1 | I13: 1 | J13: 612000 | K13: 46011 | L13: 881000 | M13: 45836 | N13: 796000 | O13: 0.69466515 | P13: 0.76884422 | Q13: 48 | R13: 45973 | S13: 45992 | T13: 47434 | U13: 46054 | V13: =DATA!$C13 = "First" -> TRUE | W13: =DATA!$U13 >= DATE(2026, 1, 1) - 30 -> TRUE | X13: =DATA!$J13 <= 800000 -> TRUE | Y13: =AND(DATA!$R13 >= DATE(2026,1,1) - 360, DATA!$R13 <=DATE(2026,1,1)) -> TRUE | Z13: =AND(DATA!$K13 >= DATE(2026,1,1) - 60, DATA!$K13 <= DATE(2026,1,1)) -> TRUE | AA13: Y
... A101: 100 | B101: RTL | C101: First | D101: 977 Cactus Way | E101: Albuquerque | F101: NM | G101: 87102 | H101: 1 | I101: 1 | J101: 796000 | K101: 45617 | L101: 1549000 | M101: 45301 | N101: 1237000 | O101: 0.51387992 | P101: 0.64349232 | Q101: 36 | R101: 45440 | S101: 45444 | T101: 46535 | U101: 46054 | V101: =DATA!$C101 = "First" -> TRUE | W101: =DATA!$U101 >= DATE(2026, 1, 1) - 30 -> TRUE | X101: =DATA!$J101 <= 800000 -> TRUE | Y101: =AND(DATA!$R101 >= DATE(2026,1,1) - 360, DATA!$R101 <=DATE(2026,1,1)) -> FALSE | Z101: =AND(DATA!$K101 >= DATE(2026,1,1) - 60, DATA!$K101 <= DATE(2026,1,1)) -> FALSE | AA101: N

Sheet Overview Summary
A1: Eligibility & Concentration Analysis Summary
A4: Part 1: Eligibility
A6: Eligibility
A7: Eligible Loan Count | B7: =COUNTIF(DATA!AA:AA, "Y") -> 22
A8: Total Eligible UPB | B8: =SUMIF(DATA!AA:AA, "Y", DATA!J:J) -> 10106000
A10: Drivers of Ineligibility | B10: Ineligible Loan Count
A11: Not first lien | B11: =COUNTIFS(DATA!$V$2:$V$101, FALSE, DATA!$AA$2:$AA$101, "N") -> 5
A12: Payment delinquent | B12: =COUNTIFS(DATA!$W$2:$W$101, FALSE, DATA!$AA$2:$AA$101, "N") -> 2
A13: UPB > $800k | B13: =COUNTIFS(DATA!$X$2:$X$101, FALSE, DATA!$AA$2:$AA$101, "N") -> 8
A14: Origination date too old | B14: =COUNTIFS(DATA!$Y$2:$Y$101, FALSE, DATA!$AA$2:$AA$101, "N") -> 56
A15: Appraisal date too old | B15: =COUNTIFS(DATA!$Z$2:$Z$101, FALSE, DATA!$AA$2:$AA$101, "N") -> 73
A18: Before starting the analysis, I first ran the conditional farmatting on the Loan ID and Address columns to check if there was any duplicate values in this dataset. After confirming data integrity, I reviewed the individual loan records to determine which loans could be included in a $200 million loan pool. Each row in the spreadsheet represents one loan. I followed the rules given in the case study to check whether each loan qualifies. These rules include first lien status, payment currentness, UPB below the $800,000 cap, and recent origination/appraisal dates relative to the January 1, 2026 funding date.A loan was marked as eligible only if it met all of the required conditions. Most loans were found to be ineligible, mainly because the appraisal or origination dates were too old.
A20: Part 2: Concerntration Analysis
A22: Category | B22: Exposure UPB | C22: Limit % | D22: Applicable limits | E22: Status
A23: California | B23: =SUMIFS(DATA!$J$2:$J$101, DATA!$F$2:$F$101, "CA", DATA!$AA$2:$AA$101, "Y") -> 3710000 | C23: 0.2 | D23: {=Table_3[Facility Size]*Table_2[[#This Row],[Limit %]]} -> 40000000 | E23: =IF( 'Overview Summary'!$D23 >= 'Overview Summary'!$B23, "Within Limit (" & TEXT('Overview Summary'!$D23 - 'Overview Summary'!$B23, "$#,##0.00") & " left)", "Breach (" & TEXT('Overview Summary'!$B23 - 'Overview Summary'!$D23, "$#,##0.00") & " over)" ) -> Within Limit ($36,290,000.00 left)
A24: UPB > $800k | B24: =SUMIFS(DATA!$J$2:$J$101, DATA!$J$2:$J$101, ">800000", DATA!$AA$2:$AA$101, "Y") -> 0 | C24: 0.05 | D24: {=Table_3[Facility Size]*Table_2[[#This Row],[Limit %]]} -> 10000000 | E24: =IF( 'Overview Summary'!$D24 >= 'Overview Summary'!$B24, "Within Limit (" & TEXT('Overview Summary'!$D24 - 'Overview Summary'!$B24, "$#,##0.00") & " left)", "Breach (" & TEXT('Overview Summary'!$B24 - 'Overview Summary'!$D24, "$#,##0.00") & " over)" ) -> Within Limit ($10,000,000.00 left)
A25: Units > 10 | B25: =SUMIFS(DATA!$J$2:$J$101, DATA!$I$2:$I$101, ">10", DATA!$AA$2:$AA$101, "Y") -> 642000 | C25: 0.15 | D25: {=Table_3[Facility Size]*Table_2[[#This Row],[Limit %]]} -> 30000000 | E25: =IF( 'Overview Summary'!$D25 >= 'Overview Summary'!$B25, "Within Limit (" & TEXT('Overview Summary'!$D25 - 'Overview Summary'!$B25, "$#,##0.00") & " left)", "Breach (" & TEXT('Overview Summary'!$B25 - 'Overview Summary'!$D25, "$#,##0.00") & " over)" ) -> Within Limit ($29,358,000.00 left) | G25: Facility Size
A26: LTAIV > 75% | B26: =SUMIFS(DATA!$J$2:$J$101, DATA!$O$2:$O$101, "> 0.75", DATA!$AA$2:$AA$101, "Y") -> 0 | C26: 0.1 | D26: {=Table_3[Facility Size]*Table_2[[#This Row],[Limit %]]} -> 20000000 | E26: =IF( 'Overview Summary'!$D26 >= 'Overview Summary'!$B26, "Within Limit (" & TEXT('Overview Summary'!$D26 - 'Overview Summary'!$B26, "$#,##0.00") & " left)", "Breach (" & TEXT('Overview Summary'!$B26 - 'Overview Summary'!$D26, "$#,##0.00") & " over)" ) -> Within Limit ($20,000,000.00 left) | G26: 200000000
A29: After identifying the eligible loans, I evaluated whether the loan pool was overly concentrated in certain risk areas. This involved checking how much of the $200 million facility was exposed to loans in a single state, loans with larger balances, loans secured by larger properties, and loans with higher leverage. For each category, I summed the loan balances and compared them to the concentration limits provided in the case study. This analysis helped determine where the portfolio was within limits and where exposure was more concentrated. All calculations assume a January 1, 2026 funding date, and no exceptions were applied beyond what was stated in the instructions.
